Metadata-Version: 2.1
Name: QA-Annotator
Version: 1.0.0
Summary: Data Annotation Tool for NLP-based Question-Answering systems
Home-page: https://github.com/impyadav/QA-Annotator
Author: Praveen Singh, Shubham Modi, Prateek Yadav
Author-email: impyadav.tech@gmail.com
License: MIT
Platform: UNKNOWN
License-File: LICENSE.txt
